CHANGES.txt
LICENSE.txt
MANIFEST.in
README.md
README_pypi.txt
setup.py
lcdapublictools/__init__.py
lcdapublictools/sqlatools.py
lcdapublictools.egg-info/PKG-INFO
lcdapublictools.egg-info/SOURCES.txt
lcdapublictools.egg-info/dependency_links.txt
lcdapublictools.egg-info/requires.txt
lcdapublictools.egg-info/top_level.txt