Metadata-Version: 1.0
Name: lcdapublictools
Version: 0.1.1
Summary: Open source tools from Lacoda.
Home-page: https://github.com/jmatthias/lcdapublictools
Author: Josh Matthias
Author-email: jmatthias4570@gmail.com
License: LICENSE.txt
Platform: UNKNOWN
